clip_table/__init__.py
clip_table/clip_table.py
clip_table-1.7.5.dist-info/DESCRIPTION.rst
clip_table-1.7.5.dist-info/METADATA
clip_table-1.7.5.dist-info/RECORD
clip_table-1.7.5.dist-info/WHEEL
clip_table-1.7.5.dist-info/metadata.json
clip_table-1.7.5.dist-info/top_level.txt
tests/__init__.py
tests/test_clip_table.py
