Metadata-Version: 2.0
Name: clip-table
Version: 1.7.5
Summary: Helper functions for copying and pasting tables.
Home-page: https://github.com/risaacr/clip_table
Author: Isaac Robinson
Author-email: isaac@rirobinson.com
License: MIT license
Keywords: clip_table
Platform: UNKNOWN
Classifier: Development Status :: 2 - Pre-Alpha
Classifier: Intended Audience :: Developers
Classifier: License :: OSI Approved :: MIT License
Classifier: Natural Language :: English
Classifier: Programming Language :: Python :: 2
Classifier: Programming Language :: Python :: 2.6
Classifier: Programming Language :: Python :: 2.7
Classifier: Programming Language :: Python :: 3
Classifier: Programming Language :: Python :: 3.3
Classifier: Programming Language :: Python :: 3.4
Classifier: Programming Language :: Python :: 3.5
Requires-Dist: pyperclip
